README.md
ez_setup.py
pert.py
setup.py
pert.egg-info/PKG-INFO
pert.egg-info/SOURCES.txt
pert.egg-info/dependency_links.txt
pert.egg-info/requires.txt
pert.egg-info/top_level.txt